[
    {
        "symbol": "♕",
        "name": "",
        "category": "Chess piece symbols copy paste"
    },
    {
        "symbol": "♛",
        "name": "",
        "category": "Chess piece symbols copy paste"
    },
    {
        "symbol": "♔",
        "name": "",
        "category": "Chess piece symbols copy paste"
    },
    {
        "symbol": "♚",
        "name": "",
        "category": "Chess piece symbols copy paste"
    },
    {
        "symbol": "👑",
        "name": "",
        "category": "Chess piece symbols copy paste"
    },
    {
        "symbol": "🤴",
        "name": "",
        "category": "Chess piece symbols copy paste"
    },
    {
        "symbol": "👸",
        "name": "",
        "category": "Chess piece symbols copy paste"
    },
    {
        "symbol": "♖",
        "name": "Chess white Rook",
        "category": "Chess piece symbols copy paste"
    },
    {
        "symbol": "♗",
        "name": "Chess White Bishop",
        "category": "Chess piece symbols copy paste"
    },
    {
        "symbol": "♘",
        "name": "Chess white Knight",
        "category": "Chess piece symbols copy paste"
    },
    {
        "symbol": "♙",
        "name": "Chess White Pawn",
        "category": "Chess piece symbols copy paste"
    },
    {
        "symbol": "♜",
        "name": "Chess Black Rook",
        "category": "Chess piece symbols copy paste"
    },
    {
        "symbol": "♝",
        "name": "Chess Black Bishop",
        "category": "Chess piece symbols copy paste"
    },
    {
        "symbol": "♞",
        "name": "Chess Black Knight",
        "category": "Chess piece symbols copy paste"
    },
    {
        "symbol": "♟",
        "name": "Chess Black Pawn",
        "category": "Chess piece symbols copy paste"
    },
    {
        "symbol": "♤",
        "name": "Chess White Spade Suit",
        "category": "Chess piece symbols copy paste"
    },
    {
        "symbol": "♠",
        "name": "Chess Black Spade Suit",
        "category": "Chess piece symbols copy paste"
    },
    {
        "symbol": "♧",
        "name": "Chess White Club Suit",
        "category": "Chess piece symbols copy paste"
    },
    {
        "symbol": "♣",
        "name": "Chess Black Club Suit",
        "category": "Chess piece symbols copy paste"
    },
    {
        "symbol": "♡",
        "name": "Chess White Heart Suit",
        "category": "Chess piece symbols copy paste"
    },
    {
        "symbol": "♥",
        "name": "Chess Black Heart Suit",
        "category": "Chess piece symbols copy paste"
    },
    {
        "symbol": "♢",
        "name": "Chess White Diamond Suit",
        "category": "Chess piece symbols copy paste"
    },
    {
        "symbol": "♦",
        "name": "Chess Black Diamond Suit",
        "category": "Chess piece symbols copy paste"
    }
]