[
    {
        "symbol": "◑.◑",
        "name": "No name",
        "category": "(꒪⌓꒪) Nervous Lenny Face"
    },
    {
        "symbol": "⊙﹏⊙",
        "name": "No name",
        "category": "(꒪⌓꒪) Nervous Lenny Face"
    },
    {
        "symbol": "●﹏●",
        "name": "No name",
        "category": "(꒪⌓꒪) Nervous Lenny Face"
    },
    {
        "symbol": "⚆ᗝ⚆",
        "name": "No name",
        "category": "(꒪⌓꒪) Nervous Lenny Face"
    },
    {
        "symbol": "(꒪⌓꒪)",
        "name": "No name",
        "category": "(꒪⌓꒪) Nervous Lenny Face"
    },
    {
        "symbol": "⊙△⊙",
        "name": "No name",
        "category": "(꒪⌓꒪) Nervous Lenny Face"
    },
    {
        "symbol": "(ʘдʘ╬)",
        "name": "No name",
        "category": "(꒪⌓꒪) Nervous Lenny Face"
    },
    {
        "symbol": "ଵ˛̼ଵ",
        "name": "No name",
        "category": "(꒪⌓꒪) Nervous Lenny Face"
    },
    {
        "symbol": "(-｡-;",
        "name": "No name",
        "category": "(꒪⌓꒪) Nervous Lenny Face"
    },
    {
        "symbol": "(ﾟωﾟ；)",
        "name": "No name",
        "category": "(꒪⌓꒪) Nervous Lenny Face"
    },
    {
        "symbol": "(ーー;)",
        "name": "No name",
        "category": "(꒪⌓꒪) Nervous Lenny Face"
    },
    {
        "symbol": "(￣□￣)",
        "name": "No name",
        "category": "(꒪⌓꒪) Nervous Lenny Face"
    },
    {
        "symbol": "（＞д＜）",
        "name": "No name",
        "category": "(꒪⌓꒪) Nervous Lenny Face"
    },
    {
        "symbol": "(ノдヽ)",
        "name": "No name",
        "category": "(꒪⌓꒪) Nervous Lenny Face"
    },
    {
        "symbol": "（／．＼）",
        "name": "No name",
        "category": "(꒪⌓꒪) Nervous Lenny Face"
    },
    {
        "symbol": "(／。＼)",
        "name": "No name",
        "category": "(꒪⌓꒪) Nervous Lenny Face"
    },
    {
        "symbol": "ヽ( ｀0´)ﾉ",
        "name": "No name",
        "category": "(꒪⌓꒪) Nervous Lenny Face"
    },
    {
        "symbol": "(ﾟдﾟ)",
        "name": "No name",
        "category": "(꒪⌓꒪) Nervous Lenny Face"
    },
    {
        "symbol": "(☍﹏⁰)",
        "name": "No name",
        "category": "(꒪⌓꒪) Nervous Lenny Face"
    },
    {
        "symbol": ")Д⊙`)",
        "name": "No name",
        "category": "(꒪⌓꒪) Nervous Lenny Face"
    },
    {
        "symbol": "(O∆O)",
        "name": "No name",
        "category": "(꒪⌓꒪) Nervous Lenny Face"
    },
    {
        "symbol": "(･д･)",
        "name": "No name",
        "category": "(꒪⌓꒪) Nervous Lenny Face"
    },
    {
        "symbol": "┗|｀O′|┛",
        "name": "No name",
        "category": "(꒪⌓꒪) Nervous Lenny Face"
    },
    {
        "symbol": "(๏д๏)",
        "name": "No name",
        "category": "(꒪⌓꒪) Nervous Lenny Face"
    },
    {
        "symbol": "（ΩДΩ）",
        "name": "No name",
        "category": "(꒪⌓꒪) Nervous Lenny Face"
    },
    {
        "symbol": "(¤﹏¤)",
        "name": "No name",
        "category": "(꒪⌓꒪) Nervous Lenny Face"
    },
    {
        "symbol": "๑ΘдΘ๑",
        "name": "No name",
        "category": "(꒪⌓꒪) Nervous Lenny Face"
    },
    {
        "symbol": "(⊃д⊂)",
        "name": "No name",
        "category": "(꒪⌓꒪) Nervous Lenny Face"
    },
    {
        "symbol": "(⊃‿⊂)",
        "name": "No name",
        "category": "(꒪⌓꒪) Nervous Lenny Face"
    },
    {
        "symbol": "o(-`д´- ｡)",
        "name": "No name",
        "category": "(꒪⌓꒪) Nervous Lenny Face"
    },
    {
        "symbol": "╰（‵□′）╯",
        "name": "No name",
        "category": "(꒪⌓꒪) Nervous Lenny Face"
    },
    {
        "symbol": "《ﾟДﾟ》",
        "name": "No name",
        "category": "(꒪⌓꒪) Nervous Lenny Face"
    },
    {
        "symbol": "（╬￣皿￣）",
        "name": "No name",
        "category": "(꒪⌓꒪) Nervous Lenny Face"
    },
    {
        "symbol": "[○･｀Д´･○]",
        "name": "No name",
        "category": "(꒪⌓꒪) Nervous Lenny Face"
    },
    {
        "symbol": "┣¨キ(*ﾟ益ﾟ*)┣¨キ",
        "name": "No name",
        "category": "(꒪⌓꒪) Nervous Lenny Face"
    }
]